lottery/__init__.py
lottery_tool-1.0.4.dist-info/METADATA
lottery_tool-1.0.4.dist-info/WHEEL
lottery_tool-1.0.4.dist-info/top_level.txt
lottery_tool-1.0.4.dist-info/RECORD
