Metadata-Version: 2.4
Name: lottery-tool
Version: 1.0.4
Summary: Tiny library for weighted random allocation
Author-email: liujunyi <liujunyi0702@petalmail.com>
Keywords: random,weighted,lottery,distribution
Classifier: Programming Language :: Python :: 3
Classifier: License :: OSI Approved :: MIT License
Classifier: Operating System :: OS Independent
Requires-Python: >=3.7
